Workbook

Sheet SAV_IT_Department_Attendance
A1: SLV IT PVT. LTD. Candidates Attendance Details
A3: Date | B3: 46235 | C3: 46236 | D3: 46237 | E3: 46238 | F3: 46239 | G3: 46240 | H3: 46241 | I3: 46242 | J3: 46243 | K3: 46244 | L3: 46245 | M3: 46246 | N3: 46247 | O3: 46248 | P3: 46249 | Q3: 46250 | R3: 46251 | S3: 46252 | T3: 46253 | U3: 46254 | V3: 46255 | W3: 46256 | X3: 46257 | Y3: 46258 | Z3: 46259 | AA3: 46260 | AB3: 46261 | AC3: 46262 | AD3: 46263 | AE3: 46264 | AF3: 46265
A4: Candidate | B4: Sat | C4: Sun | D4: Mon | E4: Tue | F4: Wed | G4: Thu | H4: Fri | I4: Sat | J4: Sun | K4: Mon | L4: Tue | M4: Wed | N4: Thu | O4: Fri | P4: Sat | Q4: Sun | R4: Mon | S4: Tue | T4: Wed | U4: Thu | V4: Fri | W4: Sat | X4: Sun | Y4: Mon | Z4: Tue | AA4: Wed | AB4: Thu | AC4: Fri | AD4: Sat | AE4: Sun | AF4: Mon
A5: Arjun Kumar | B5: H | C5: H | D5: P | E5: P | F5: P | G5: P | H5: A | I5: H | J5: H | K5: P | L5: P | M5: SL | N5: P | O5: P | P5: H | Q5: H | R5: P | S5: A | T5: P | U5: P | V5: P | W5: H | X5: H | Y5: P | Z5: P | AA5: P | AB5: A | AC5: P | AD5: H | AE5: H | AF5: P
A6: Priya Sharma | B6: H | C6: H | D6: P | E6: A | F6: P | G6: P | H6: P | I6: H | J6: H | K6: P | L6: P | M6: A | N6: P | O6: P | P6: H | Q6: H | R6: P | S6: P | T6: SL | U6: A | V6: P | W6: H | X6: H | Y6: P | Z6: P | AA6: A | AB6: P | AC6: P | AD6: H | AE6: H | AF6: P
A7: Rahul Verma | B7: H | C7: H | D7: P | E7: P | F7: A | G7: P | H7: P | I7: H | J7: H | K7: P | L7: A | M7: P | N7: P | O7: P | P7: H | Q7: H | R7: A | S7: P | T7: P | U7: P | V7: P | W7: H | X7: H | Y7: P | Z7: A | AA7: P | AB7: P | AC7: P | AD7: H | AE7: H | AF7: P
A8: Sneha Reddy | B8: H | C8: H | D8: A | E8: P | F8: P | G8: P | H8: P | I8: H | J8: H | K8: P | L8: P | M8: P | N8: A | O8: P | P8: H | Q8: H | R8: P | S8: P | T8: NSL | U8: P | V8: A | W8: H | X8: H | Y8: P | Z8: P | AA8: P | AB8: A | AC8: P | AD8: H | AE8: H | AF8: P
A9: Kiran Rao | B9: H | C9: H | D9: P | E9: P | F9: P | G9: A | H9: P | I9: H | J9: H | K9: P | L9: P | M9: P | N9: P | O9: A | P9: H | Q9: H | R9: P | S9: A | T9: P | U9: P | V9: SL | W9: H | X9: H | Y9: P | Z9: P | AA9: A | AB9: P | AC9: P | AD9: H | AE9: H | AF9: P
A10: Meena Patel | B10: H | C10: H | D10: P | E10: P | F10: A | G10: P | H10: P | I10: H | J10: H | K10: A | L10: P | M10: P | N10: P | O10: P | P10: H | Q10: H | R10: P | S10: P | T10: A | U10: SL | V10: P | W10: H | X10: H | Y10: P | Z10: A | AA10: P | AB10: P | AC10: P | AD10: H | AE10: H | AF10: P
A11: Vikram Singh | B11: H | C11: H | D11: P | E11: A | F11: P | G11: P | H11: P | I11: H | J11: H | K11: P | L11: P | M11: A | N11: P | O11: P | P11: H | Q11: H | R11: A | S11: P | T11: P | U11: P | V11: P | W11: H | X11: H | Y11: P | Z11: P | AA11: P | AB11: NSL | AC11: P | AD11: H | AE11: H | AF11: P
A12: Suresh Babu | B12: H | C12: H | D12: A | E12: P | F12: P | G12: P | H12: P | I12: H | J12: H | K12: P | L12: P | M12: P | N12: A | O12: P | P12: H | Q12: H | R12: P | S12: A | T12: P | U12: P | V12: P | W12: H | X12: H | Y12: P | Z12: P | AA12: NSL | AB12: P | AC12: A | AD12: H | AE12: H | AF12: P
A13: Anjali Menon | B13: H | C13: H | D13: P | E13: P | F13: A | G13: P | H13: P | I13: H | J13: H | K13: P | L13: P | M13: A | N13: P | O13: P | P13: H | Q13: H | R13: P | S13: P | T13: P | U13: SL | V13: P | W13: H | X13: H | Y13: P | Z13: A | AA13: P | AB13: P | AC13: P | AD13: H | AE13: H | AF13: A

Sheet Candidates_Details
A1: SLV IT PVT. LTD. Candidates Details
A3: Emp_ID | B3: Employee_Name | C3: Designation | D3: Date_of_Joining | E3: PAN_Number | F3: Department | G3: Date_of_Birth | H3: Bank_Account_Number | I3: Bank_Name | J3: Basic_Salary | K3: HRA | L3: Conveyance | M3: Medical_Allowance | N3: Special_Allowance | O3: Gross_Salary | P3: Annual Salary | Q3: Taxable Income | R3: Slab Tax | S3: 87A Rebate | T3: Tax After Rebate | U3: 4% Cess | V3: Final Annual Tax | W3: Final Monthly Tax
A4: IT001 | B4: Arjun Kumar | C4: Software Engineer | D4: 44576 | E4: XXXXX0001X | F4: IT | G4: 35562 | H4: 100000000001 | I4: SBI | J4: 35000 | K4: 14000 | L4: 3000 | M4: 2000 | N4: 6000 | O4: 60000 | P4: =O4*12 -> 720000 | Q4: =P4-75000 -> 645000 | R4: {=_xlfn.IFS(Q4<=400000,0,Q4<=800000,(Q4-400000)*5%,Q4<=1200000,20000+(Q4-800000)*10%,Q4<=1600000,60000+(Q4-1200000)*15%,Q4<=2000000,120000+(Q4-1600000)*20%,Q4<=2400000,200000+(Q4-2000000)*25%,Q4>2400000,300000+(Q4-2400000)*30%)} -> 12250 | S4: =IF(Q4<=1200000,MIN(R4,600000),0) -> 12250 | T4: =R4-S4 -> 0 | U4: =T4*4% -> 0 | V4: =T4+(T4*4%) -> 0 | W4: =V4/12 -> 0
A5: IT002 | B5: Priya Sharma | C5: Senior Software Engineer | D5: 44265 | E5: XXXXX0002X | F5: IT | G5: 34936 | H5: 100000000002 | I5: HDFC Bank | J5: 50000 | K5: 20000 | L5: 4000 | M5: 2500 | N5: 8500 | O5: 85000 | P5: =O5*12 -> 1020000 | Q5: =P5-75000 -> 945000 | R5: {=_xlfn.IFS(Q5<=400000,0,Q5<=800000,(Q5-400000)*5%,Q5<=1200000,20000+(Q5-800000)*10%,Q5<=1600000,60000+(Q5-1200000)*15%,Q5<=2000000,120000+(Q5-1600000)*20%,Q5<=2400000,200000+(Q5-2000000)*25%,Q5>2400000,300000+(Q5-2400000)*30%)} -> 34500 | S5: =IF(Q5<=1200000,MIN(R5,600000),0) -> 34500 | T5: =R5-S5 -> 0 | U5: =T5*4% -> 0 | V5: =T5+(T5*4%) -> 0 | W5: =V5/12 -> 0
A6: IT003 | B6: Rahul Verma | C6: Data Analyst | D6: 45097 | E6: XXXXX0003X | F6: IT | G6: 36482 | H6: 100000000003 | I6: ICICI Bank | J6: 30000 | K6: 12000 | L6: 3000 | M6: 2000 | N6: 5000 | O6: 52000 | P6: =O6*12 -> 624000 | Q6: =P6-75000 -> 549000 | R6: {=_xlfn.IFS(Q6<=400000,0,Q6<=800000,(Q6-400000)*5%,Q6<=1200000,20000+(Q6-800000)*10%,Q6<=1600000,60000+(Q6-1200000)*15%,Q6<=2000000,120000+(Q6-1600000)*20%,Q6<=2400000,200000+(Q6-2000000)*25%,Q6>2400000,300000+(Q6-2400000)*30%)} -> 7450 | S6: =IF(Q6<=1200000,MIN(R6,600000),0) -> 7450 | T6: =R6-S6 -> 0 | U6: =T6*4% -> 0 | V6: =T6+(T6*4%) -> 0 | W6: =V6/12 -> 0
A7: IT004 | B7: Sneha Reddy | C7: Data Scientist | D7: 44079 | E7: XXXXX0004X | F7: IT | G7: 34372 | H7: 100000000004 | I7: Axis Bank | J7: 60000 | K7: 24000 | L7: 5000 | M7: 3000 | N7: 13000 | O7: 105000 | P7: =O7*12 -> 1260000 | Q7: =P7-75000 -> 1185000 | R7: {=_xlfn.IFS(Q7<=400000,0,Q7<=800000,(Q7-400000)*5%,Q7<=1200000,20000+(Q7-800000)*10%,Q7<=1600000,60000+(Q7-1200000)*15%,Q7<=2000000,120000+(Q7-1600000)*20%,Q7<=2400000,200000+(Q7-2000000)*25%,Q7>2400000,300000+(Q7-2400000)*30%)} -> 58500 | S7: =IF(Q7<=1200000,MIN(R7,600000),0) -> 58500 | T7: =R7-S7 -> 0 | U7: =T7*4% -> 0 | V7: =T7+(T7*4%) -> 0 | W7: =V7/12 -> 0
A8: IT005 | B8: Kiran Rao | C8: DevOps Engineer | D8: 44604 | E8: XXXXX0005X | F8: IT | G8: 35246 | H8: 100000000005 | I8: Kotak Bank | J8: 45000 | K8: 18000 | L8: 4000 | M8: 2500 | N8: 7500 | O8: 77000 | P8: =O8*12 -> 924000 | Q8: =P8-75000 -> 849000 | R8: {=_xlfn.IFS(Q8<=400000,0,Q8<=800000,(Q8-400000)*5%,Q8<=1200000,20000+(Q8-800000)*10%,Q8<=1600000,60000+(Q8-1200000)*15%,Q8<=2000000,120000+(Q8-1600000)*20%,Q8<=2400000,200000+(Q8-2000000)*25%,Q8>2400000,300000+(Q8-2400000)*30%)} -> 24900 | S8: =IF(Q8<=1200000,MIN(R8,600000),0) -> 24900 | T8: =R8-S8 -> 0 | U8: =T8*4% -> 0 | V8: =T8+(T8*4%) -> 0 | W8: =V8/12 -> 0
A9: IT006 | B9: Meena Patel | C9: QA Engineer | D9: 45125 | E9: XXXXX0006X | F9: IT | G9: 36052 | H9: 100000000006 | I9: SBI | J9: 28000 | K9: 11200 | L9: 2500 | M9: 1500 | N9: 4800 | O9: 48000 | P9: =O9*12 -> 576000 | Q9: =P9-75000 -> 501000 | R9: {=_xlfn.IFS(Q9<=400000,0,Q9<=800000,(Q9-400000)*5%,Q9<=1200000,20000+(Q9-800000)*10%,Q9<=1600000,60000+(Q9-1200000)*15%,Q9<=2000000,120000+(Q9-1600000)*20%,Q9<=2400000,200000+(Q9-2000000)*25%,Q9>2400000,300000+(Q9-2400000)*30%)} -> 5050 | S9: =IF(Q9<=1200000,MIN(R9,600000),0) -> 5050 | T9: =R9-S9 -> 0 | U9: =T9*4% -> 0 | V9: =T9+(T9*4%) -> 0 | W9: =V9/12 -> 0
A10: IT007 | B10: Vikram Singh | C10: Tech Lead | D10: 43794 | E10: XXXXX0007X | F10: IT | G10: 33625 | H10: 100000000007 | I10: HDFC Bank | J10: 75000 | K10: 30000 | L10: 6000 | M10: 3500 | N10: 15500 | O10: 130000 | P10: =O10*12 -> 1560000 | Q10: =P10-75000 -> 1485000 | R10: {=_xlfn.IFS(Q10<=400000,0,Q10<=800000,(Q10-400000)*5%,Q10<=1200000,20000+(Q10-800000)*10%,Q10<=1600000,60000+(Q10-1200000)*15%,Q10<=2000000,120000+(Q10-1600000)*20%,Q10<=2400000,200000+(Q10-2000000)*25%,Q10>2400000,300000+(Q10-2400000)*30%)} -> 102750 | S10: =IF(Q10<=1200000,MIN(R10,600000),0) -> 0 | T10: =R10-S10 -> 102750 | U10: =T10*4% -> 4110 | V10: =T10+(T10*4%) -> 106860 | W10: =V10/12 -> 8905
A11: IT009 | B11: Suresh Babu | C11: System Administrator | D11: 44424 | E11: XXXXX0009X | F11: IT | G11: 34769 | H11: 100000000009 | I11: Axis Bank | J11: 40000 | K11: 16000 | L11: 3500 | M11: 2000 | N11: 6500 | O11: 68000 | P11: =O11*12 -> 816000 | Q11: =P11-75000 -> 741000 | R11: {=_xlfn.IFS(Q11<=400000,0,Q11<=800000,(Q11-400000)*5%,Q11<=1200000,20000+(Q11-800000)*10%,Q11<=1600000,60000+(Q11-1200000)*15%,Q11<=2000000,120000+(Q11-1600000)*20%,Q11<=2400000,200000+(Q11-2000000)*25%,Q11>2400000,300000+(Q11-2400000)*30%)} -> 17050 | S11: =IF(Q11<=1200000,MIN(R11,600000),0) -> 17050 | T11: =R11-S11 -> 0 | U11: =T11*4% -> 0 | V11: =T11+(T11*4%) -> 0 | W11: =V11/12 -> 0
A12: IT010 | B12: Anjali Menon | C12: Project Manager | D12: 43103 | E12: XXXXX0010X | F12: IT | G12: 33082 | H12: 100000000010 | I12: Kotak Bank | J12: 85000 | K12: 34000 | L12: 7000 | M12: 4000 | N12: 20000 | O12: 150000 | P12: =O12*12 -> 1800000 | Q12: =P12-75000 -> 1725000 | R12: {=_xlfn.IFS(Q12<=400000,0,Q12<=800000,(Q12-400000)*5%,Q12<=1200000,20000+(Q12-800000)*10%,Q12<=1600000,60000+(Q12-1200000)*15%,Q12<=2000000,120000+(Q12-1600000)*20%,Q12<=2400000,200000+(Q12-2000000)*25%,Q12>2400000,300000+(Q12-2400000)*30%)} -> 145000 | S12: =IF(Q12<=1200000,MIN(R12,600000),0) -> 0 | T12: =R12-S12 -> 145000 | U12: =T12*4% -> 5800 | V12: =T12+(T12*4%) -> 150800 | W12: =V12/12 -> 12566.667
K21: {=_xlfn.IFS( H27*12<=400000,0, H27*12<=800000,H27*5%, H27*12<=1200000,H27*10%, H27*12<=1600000,H27*15%, H27*12<=2000000,H27*20%, H27*12<=2400000,H27*25%, H27*12>2400000,H27*30% )} -> 0

Sheet Payroll_Sheet
F3: SLV IT PVT. LTD.
N4: Employee Name
F5: LBC Tech Knowledge Park,Bhanarggtha Road,Bengaluru,560061. | N5: Anjali Menon
F6: PAY SLIP OF THE MONTH OF AUGUST 2026
F7: Attendance Details
F8: Days in Month: | H8: 31 | I8: Approved sick Leave: | K8: =COUNTIF(INDEX(SAV_IT_Department_Attendance!$B$5:$AF$13,MATCH(Payroll_Sheet!$H$13,SAV_IT_Department_Attendance!$A$5:$A$13,0),0),"SL") -> 1
F9: Number of Days Worked: | H9: =COUNTIF(INDEX(SAV_IT_Department_Attendance!$B$5:$AF$13,MATCH(Payroll_Sheet!$H$13,SAV_IT_Department_Attendance!$A$5:$A$13,0),0),"P") -> 16 | I9: Not Approved sick Leave: | K9: =COUNTIF(INDEX(SAV_IT_Department_Attendance!$B$5:$AF$13,MATCH(Payroll_Sheet!$H$13,SAV_IT_Department_Attendance!$A$5:$A$13,0),0),"NSL") -> 0
F10: Number of Days Absent: | H10: =COUNTIF(INDEX(SAV_IT_Department_Attendance!$B$5:$AF$13,MATCH(Payroll_Sheet!$H$13,SAV_IT_Department_Attendance!$A$5:$A$13,0),0),"A") -> 4 | I10: Total Days Worked: | K10: =COUNTIF(INDEX(SAV_IT_Department_Attendance!$B$5:$AF$13,MATCH(Payroll_Sheet!$H$13,SAV_IT_Department_Attendance!$A$5:$A$13,0),0),"H")+H9 -> 26
F11: Salary Details
F12: Employee Code: | H12: =INDEX(Candidates_Details!A:A,MATCH(Payroll_Sheet!H13,Candidates_Details!B:B,0)) -> IT010 | I12: Department: | K12: =INDEX(Candidates_Details!F:F,MATCH(Payroll_Sheet!H13,Candidates_Details!B:B,0)) -> IT
F13: Employee Name: | H13: =N5 -> Anjali Menon | I13: Location: | K13: Bengaluru
F14: Designation: | H14: =INDEX(Candidates_Details!C:C,MATCH(Payroll_Sheet!H13,Candidates_Details!B:B,0)) -> Project Manager | I14: Date Of Birth: | K14: =INDEX(Candidates_Details!G:G,MATCH(Payroll_Sheet!H13,Candidates_Details!B:B,0)) -> 33082
F15: Date of Joining: | H15: =INDEX(Candidates_Details!D:D,MATCH(Payroll_Sheet!H13,Candidates_Details!B:B,0)) -> 43103 | I15: Bank Account Number: | K15: =INDEX(Candidates_Details!H:H,MATCH(Payroll_Sheet!H13,Candidates_Details!B:B,0)) -> 100000000010
F16: PAN#: | H16: =INDEX(Candidates_Details!E:E,MATCH(Payroll_Sheet!H13,Candidates_Details!B:B,0)) -> XXXXX0010X | I16: Bank Name: | K16: =INDEX(Candidates_Details!I:I,MATCH(Payroll_Sheet!H13,Candidates_Details!B:B,0)) -> Kotak Bank
F17: UAN: | H17: - | I17: - | K17: -
F18: Earnings | H18: INR | I18: Deduction | K18: INR
F19: Basic_Salary: | H19: =VLOOKUP(H13,Candidates_Details!B:J,9,FALSE) -> 85000 | I19: Professional Tax: | K19: =VLOOKUP(H13,Candidates_Details!B:W,22,FALSE) -> 12566.667
F20: HRA: | H20: =VLOOKUP(H13,Candidates_Details!B:K,10,FALSE) -> 34000 | I20: Provider Fund: | K20: =H19*12% -> 10200
F21: Conveyance: | H21: =VLOOKUP(H13,Candidates_Details!B:L,11,FALSE) -> 7000 | I21: ESI: | K21: =H25*0.75% -> 1125
F22: Medical_Allowance: | H22: =VLOOKUP(H13,Candidates_Details!B:M,12,FALSE) -> 4000
F23: Special_Allowance: | H23: =VLOOKUP(H13,Candidates_Details!B:N,13,FALSE) -> 20000
F25: Total_Gross_Salary: | H25: =SUM(H19:H23) -> 150000 | I25: Total_Deductions: | K25: =(H25-SUM(K19:K21))/31*K10 -> 105768.28
F27: Net Salary: | G27: =K25 -> 105768.28
F28: Take Home Salary: | G28: =G27 -> 105768.28
